fish_multiplier
how_many_fish
